join_eos_exif/OrthoRenamer.py
join_eos_exif/__init__.py
join_eos_exif-1.2.0.dist-info/WHEEL
join_eos_exif-1.2.0.dist-info/METADATA
join_eos_exif-1.2.0.dist-info/RECORD
