Metadata-Version: 2.1
Name: join-eos-exif
Version: 1.2.0
Summary: Join EOS files to images using EXIF data
License: MIT
Author: Taylor Denouden
Author-email: taylor.denouden@hakai.org
Requires-Python: >=3.8.1,<3.11
Classifier: License :: OSI Approved :: MIT License
Classifier: Programming Language :: Python :: 3
Classifier: Programming Language :: Python :: 3.9
Classifier: Programming Language :: Python :: 3.10
Requires-Dist: PyQt6 (>=6.4.0,<7.0.0)
Requires-Dist: numpy (>=1.23.5,<2.0.0)
Requires-Dist: pandas (>=2.0.1,<3.0.0)
